Workbook

Sheet Read Me
B2: Borssele 1 & 2 — DCF Project Model
B3: Deterministic model in Excel | Monte Carlo & ex-post analysis in Python
B5: Tabs
B6: Assumptions: Change a value and the whole model recalculates.
B7: Price Data: NL wholesale day-ahead prices (ENTSO-E), monthly + yearly averages.
B8: Model (ex-ante): annual cash flow with the fixed 2016 price assumption (EUR 30/MWh).
B9: Ex-Post: same model, but with actual yearly prices 2021 to mid-2026, and a separate
B10: post-2026 price assumption (default EUR 80/MWh) for the remaining years.
B11: Dashboard: key outputs, ex-ante vs ex-post, valuation benchmarks, and the CREG CAPEX check.
B14: SDE+ revenue logic (the core of this project)
B15: Price per MWh in years 1-15: price = market + MAX(0 ; tender - MAX(market ; floor)).
B16: Above the tender amount (72.70): producer receives the full market price, no subsidy.
... B29: tax shield. A negative result shows the bid only worked with costs below the CREG estimate.

Sheet Assumptions
A1: Assumptions
A4: Parameter | B4: Value | C4: Unit | D4: Source / note
A5: Physical & production
A6: Capacity | B6: 752 | C6: MW | D6: Orsted
A7: Capacity factor | B7: 0.5 | C7: fraction | D7: CREG 2016
A8: Full-load hours | B8: =B7*8760 -> 4380 | C8: hours/yr | D8: CF x 8760
A9: Gross annual production | B9: =B6*B8 -> 3293760 | C9: MWh/yr | D9: MW x full-load hours
A10: Annual degradation | B10: 0 | C10: fraction | D10: Wind: ~0 (input; test 0.5-1%)
A11: CAPEX & decommissioning
A12: CAPEX total (EIB) | B12: 1491 | C12: EUR m | D12: EIB 2020 (total cost)
A13: CAPEX total | B13: =B12*1000000 -> 1491000000 | C13: EUR | D13: m x 1,000,000
A14: CAPEX total (CREG, check) | B14: 1891 | C14: EUR m | D14: CREG 2016 (2.515m/MW)
A15: Decommissioning cost | B15: 42 | C15: EUR m | D15: CREG 2016
A16: Decommissioning cost | B16: =B15*1000000 -> 42000000 | C16: EUR | D16: m x 1,000,000
A17: OPEX
A18: OPEX variable | B18: 9.59 | C18: EUR/MWh | D18: CREG 2016
A19: OPEX fixed | B19: 40350 | C19: EUR/MW/yr | D19: CREG 2016
A20: OPEX inflation | B20: 0.02 | C20: fraction/yr | D20: Assumption
A21: Revenue / SDE+
A22: Tender amount (base amount) | B22: 72.7 | C22: EUR/MWh | D22: CREG / Orsted / EZ
A23: Floor (base electricity price) | B23: 29 | C23: EUR/MWh | D23: RVO (2.9 ct/kWh)
A24: Subsidy period | B24: 15 | C24: years | D24: Court of Audit / RVO
A25: Market price ex-ante | B25: 30 | C25: EUR/MWh | D25: CREG 2016 (Monte Carlo centre)
A26: Market price after actuals | B26: 80 | C26: EUR/MWh | D26: Post-2026 tail: ~88 realised x ~90% capture
A27: Financing & WACC
A28: Equity share | B28: 0.3 | C28: fraction | D28: CREG 2016
A29: Debt share | B29: 0.7 | C29: fraction | D29: CREG 2016
A30: Cost of debt | B30: 0.025 | C30: fraction | D30: CREG 2016
A31: Return on equity | B31: 0.1 | C31: fraction | D31: CREG + Bloomberg
A32: Corporate tax rate | B32: 0.258 | C32: fraction | D32: NL CIT — verify year
A33: WACC (after tax) | B33: =B28*B31+B29*B30*(1-B32) -> 0.042985 | C33: fraction | D33: own calculation
A34: Timeline
A35: COD (start of operations) | B35: 2021 | C35: year | D35: Orsted Q4 2020
A36: Operational life | B36: 25 | C36: years | D36: CREG 2016

Sheet Price Data
A1: NL wholesale day-ahead prices
A2: Source: ENTSO-E
E3: Yearly averages
E4: Year | F4: Avg (EUR/MWh)
E5: 2015 | F5: =AVERAGEIF($C$20:$C$158,E5,$B$20:$B$158) -> 40.07
E6: 2016 | F6: =AVERAGEIF($C$20:$C$158,E6,$B$20:$B$158) -> 32.2225
E7: 2017 | F7: =AVERAGEIF($C$20:$C$158,E7,$B$20:$B$158) -> 39.329167
E8: 2018 | F8: =AVERAGEIF($C$20:$C$158,E8,$B$20:$B$158) -> 52.489167
E9: 2019 | F9: =AVERAGEIF($C$20:$C$158,E9,$B$20:$B$158) -> 41.215833
E10: 2020 | F10: =AVERAGEIF($C$20:$C$158,E10,$B$20:$B$158) -> 32.2275
E11: 2021 | F11: =AVERAGEIF($C$20:$C$158,E11,$B$20:$B$158) -> 102.64833
E12: 2022 | F12: =AVERAGEIF($C$20:$C$158,E12,$B$20:$B$158) -> 241.20417
E13: 2023 | F13: =AVERAGEIF($C$20:$C$158,E13,$B$20:$B$158) -> 96.134167
E14: 2024 | F14: =AVERAGEIF($C$20:$C$158,E14,$B$20:$B$158) -> 77.239167
E15: 2025 | F15: =AVERAGEIF($C$20:$C$158,E15,$B$20:$B$158) -> 87.55
E16: 2026 | F16: =AVERAGEIF($C$20:$C$158,E16,$B$20:$B$158) -> 96.497143
A19: Month | B19: Price (EUR/MWh) | C19: Year
A20: 2015-01 | B20: 40.51 | C20: 2015
A21: 2015-02 | B21: 46.37 | C21: 2015
A22: 2015-03 | B22: 42.18 | C22: 2015
A23: 2015-04 | B23: 41.4 | C23: 2015
A24: 2015-05 | B24: 37.34 | C24: 2015
A25: 2015-06 | B25: 38.73 | C25: 2015
A26: 2015-07 | B26: 42.19 | C26: 2015
A27: 2015-08 | B27: 38.87 | C27: 2015
A28: 2015-09 | B28: 39.65 | C28: 2015
A29: 2015-10 | B29: 41.45 | C29: 2015
A30: 2015-11 | B30: 38.44 | C30: 2015
A31: 2015-12 | B31: 33.71 | C31: 2015
... A158: 2026-07 | B158: 87.02 | C158: 2026

Sheet Model (ex-ante)
A1: Model Ex-Ante (deterministic)
A4: Calendar year | C4: =Assumptions!$B$35-1 -> 2020 | D4: =Assumptions!$B$35+0 -> 2021 | E4: =Assumptions!$B$35+1 -> 2022 | F4: =Assumptions!$B$35+2 -> 2023 | G4: =Assumptions!$B$35+3 -> 2024 | H4: =Assumptions!$B$35+4 -> 2025 | I4: =Assumptions!$B$35+5 -> 2026 | J4: =Assumptions!$B$35+6 -> 2027 | K4: =Assumptions!$B$35+7 -> 2028 | L4: =Assumptions!$B$35+8 -> 2029 | M4: =Assumptions!$B$35+9 -> 2030 | N4: =Assumptions!$B$35+10 -> 2031 | O4: =Assumptions!$B$35+11 -> 2032 | P4: =Assumptions!$B$35+12 -> 2033 | Q4: =Assumptions!$B$35+13 -> 2034 | R4: =Assumptions!$B$35+14 -> 2035 | S4: =Assumptions!$B$35+15 -> 2036 | T4: =Assumptions!$B$35+16 -> 2037 | U4: =Assumptions!$B$35+17 -> 2038 | V4: =Assumptions!$B$35+18 -> 2039 | W4: =Assumptions!$B$35+19 -> 2040 | X4: =Assumptions!$B$35+20 -> 2041 | Y4: =Assumptions!$B$35+21 -> 2042 | Z4: =Assumptions!$B$35+22 -> 2043 | AA4: =Assumptions!$B$35+23 -> 2044 | AB4: =Assumptions!$B$35+24 -> 2045
A5: Operational year | C5: 0 | D5: 1 | E5: 2 | F5: 3 | G5: 4 | H5: 5 | I5: 6 | J5: 7 | K5: 8 | L5: 9 | M5: 10 | N5: 11 | O5: 12 | P5: 13 | Q5: 14 | R5: 15 | S5: 16 | T5: 17 | U5: 18 | V5: 19 | W5: 20 | X5: 21 | Y5: 22 | Z5: 23 | AA5: 24 | AB5: 25
A6: Subsidy active (1/0) | C6: 0 | D6: =IF(D5<=Assumptions!$B$24,1,0) -> 1 | E6: =IF(E5<=Assumptions!$B$24,1,0) -> 1 | F6: =IF(F5<=Assumptions!$B$24,1,0) -> 1 | G6: =IF(G5<=Assumptions!$B$24,1,0) -> 1 | H6: =IF(H5<=Assumptions!$B$24,1,0) -> 1 | I6: =IF(I5<=Assumptions!$B$24,1,0) -> 1 | J6: =IF(J5<=Assumptions!$B$24,1,0) -> 1 | K6: =IF(K5<=Assumptions!$B$24,1,0) -> 1 | ... AB6: =IF(AB5<=Assumptions!$B$24,1,0) -> 0
A8: PRODUCTION
A9: Degradation factor | C9: 0 | D9: =(1-Assumptions!$B$10)^(D5-1) -> 1 | E9: =(1-Assumptions!$B$10)^(E5-1) -> 1 | F9: =(1-Assumptions!$B$10)^(F5-1) -> 1 | G9: =(1-Assumptions!$B$10)^(G5-1) -> 1 | H9: =(1-Assumptions!$B$10)^(H5-1) -> 1 | I9: =(1-Assumptions!$B$10)^(I5-1) -> 1 | J9: =(1-Assumptions!$B$10)^(J5-1) -> 1 | K9: =(1-Assumptions!$B$10)^(K5-1) -> 1 | ... AB9: =(1-Assumptions!$B$10)^(AB5-1) -> 1
A10: Net production (MWh) | C10: 0 | D10: =Assumptions!$B$9*D9 -> 3293760 | E10: =Assumptions!$B$9*E9 -> 3293760 | F10: =Assumptions!$B$9*F9 -> 3293760 | G10: =Assumptions!$B$9*G9 -> 3293760 | H10: =Assumptions!$B$9*H9 -> 3293760 | I10: =Assumptions!$B$9*I9 -> 3293760 | J10: =Assumptions!$B$9*J9 -> 3293760 | K10: =Assumptions!$B$9*K9 -> 3293760 | ... AB10: =Assumptions!$B$9*AB9 -> 3293760
A11: REVENUE
A12: Market price (EUR/MWh) | C12: 0 | D12: =Assumptions!$B$25 -> 30 | E12: =Assumptions!$B$25 -> 30 | F12: =Assumptions!$B$25 -> 30 | G12: =Assumptions!$B$25 -> 30 | H12: =Assumptions!$B$25 -> 30 | I12: =Assumptions!$B$25 -> 30 | J12: =Assumptions!$B$25 -> 30 | K12: =Assumptions!$B$25 -> 30 | ... AB12: =Assumptions!$B$25 -> 30
A13: Subsidy (EUR/MWh) | C13: 0 | D13: =IF(D6=1,MAX(0,Assumptions!$B$22-MAX(D12,Assumptions!$B$23)),0) -> 42.7 | E13: =IF(E6=1,MAX(0,Assumptions!$B$22-MAX(E12,Assumptions!$B$23)),0) -> 42.7 | F13: =IF(F6=1,MAX(0,Assumptions!$B$22-MAX(F12,Assumptions!$B$23)),0) -> 42.7 | G13: =IF(G6=1,MAX(0,Assumptions!$B$22-MAX(G12,Assumptions!$B$23)),0) -> 42.7 | H13: =IF(H6=1,MAX(0,Assumptions!$B$22-MAX(H12,Assumptions!$B$23)),0) -> 42.7 | I13: =IF(I6=1,MAX(0,Assumptions!$B$22-MAX(I12,Assumptions!$B$23)),0) -> 42.7 | J13: =IF(J6=1,MAX(0,Assumptions!$B$22-MAX(J12,Assumptions!$B$23)),0) -> 42.7 | K13: =IF(K6=1,MAX(0,Assumptions!$B$22-MAX(K12,Assumptions!$B$23)),0) -> 42.7 | ... AB13: =IF(AB6=1,MAX(0,Assumptions!$B$22-MAX(AB12,Assumptions!$B$23)),0) -> 0
A14: Total price (EUR/MWh) | C14: 0 | D14: =D12+D13 -> 72.7 | E14: =E12+E13 -> 72.7 | F14: =F12+F13 -> 72.7 | G14: =G12+G13 -> 72.7 | H14: =H12+H13 -> 72.7 | I14: =I12+I13 -> 72.7 | J14: =J12+J13 -> 72.7 | K14: =K12+K13 -> 72.7 | ... AB14: =AB12+AB13 -> 30
A15: Total revenue (EUR) | C15: 0 | D15: =D10*D14 -> 239456352 | E15: =E10*E14 -> 239456352 | F15: =F10*F14 -> 239456352 | G15: =G10*G14 -> 239456352 | H15: =H10*H14 -> 239456352 | I15: =I10*I14 -> 239456352 | J15: =J10*J14 -> 239456352 | K15: =K10*K14 -> 239456352 | ... AB15: =AB10*AB14 -> 98812800
A16: COSTS
A17: OPEX variable (EUR) | C17: 0 | D17: =Assumptions!$B$18*(1+Assumptions!$B$20)^(D5-1)*D10 -> 31587158 | E17: =Assumptions!$B$18*(1+Assumptions!$B$20)^(E5-1)*E10 -> 32218902 | F17: =Assumptions!$B$18*(1+Assumptions!$B$20)^(F5-1)*F10 -> 32863280 | G17: =Assumptions!$B$18*(1+Assumptions!$B$20)^(G5-1)*G10 -> 33520545 | H17: =Assumptions!$B$18*(1+Assumptions!$B$20)^(H5-1)*H10 -> 34190956 | I17: =Assumptions!$B$18*(1+Assumptions!$B$20)^(I5-1)*I10 -> 34874775 | J17: =Assumptions!$B$18*(1+Assumptions!$B$20)^(J5-1)*J10 -> 35572271 | K17: =Assumptions!$B$18*(1+Assumptions!$B$20)^(K5-1)*K10 -> 36283716 | ... AB17: =Assumptions!$B$18*(1+Assumptions!$B$20)^(AB5-1)*AB10 -> 50805962
A18: OPEX fixed (EUR) | C18: 0 | D18: =Assumptions!$B$19*(1+Assumptions!$B$20)^(D5-1)*Assumptions!$B$6 -> 30343200 | E18: =Assumptions!$B$19*(1+Assumptions!$B$20)^(E5-1)*Assumptions!$B$6 -> 30950064 | F18: =Assumptions!$B$19*(1+Assumptions!$B$20)^(F5-1)*Assumptions!$B$6 -> 31569065 | G18: =Assumptions!$B$19*(1+Assumptions!$B$20)^(G5-1)*Assumptions!$B$6 -> 32200447 | H18: =Assumptions!$B$19*(1+Assumptions!$B$20)^(H5-1)*Assumptions!$B$6 -> 32844456 | I18: =Assumptions!$B$19*(1+Assumptions!$B$20)^(I5-1)*Assumptions!$B$6 -> 33501345 | J18: =Assumptions!$B$19*(1+Assumptions!$B$20)^(J5-1)*Assumptions!$B$6 -> 34171372 | K18: =Assumptions!$B$19*(1+Assumptions!$B$20)^(K5-1)*Assumptions!$B$6 -> 34854799 | ... AB18: =Assumptions!$B$19*(1+Assumptions!$B$20)^(AB5-1)*Assumptions!$B$6 -> 48805133
A19: Total OPEX (EUR) | C19: 0 | D19: =D17+D18 -> 61930358 | E19: =E17+E18 -> 63168966 | F19: =F17+F18 -> 64432345 | G19: =G17+G18 -> 65720992 | H19: =H17+H18 -> 67035412 | I19: =I17+I18 -> 68376120 | J19: =J17+J18 -> 69743642 | K19: =K17+K18 -> 71138515 | ... AB19: =AB17+AB18 -> 99611095
A20: RESULT
A21: EBITDA (EUR) | C21: 0 | D21: =D15-D19 -> 1.7752599e+08 | E21: =E15-E19 -> 1.7628739e+08 | F21: =F15-F19 -> 1.7502401e+08 | G21: =G15-G19 -> 1.7373536e+08 | H21: =H15-H19 -> 1.7242094e+08 | I21: =I15-I19 -> 1.7108023e+08 | J21: =J15-J19 -> 1.6971271e+08 | K21: =K15-K19 -> 1.6831784e+08 | ... AB21: =AB15-AB19 -> -798295.32
A22: Depreciation (EUR) | C22: 0 | D22: =Assumptions!$B$13/Assumptions!$B$36 -> 59640000 | E22: =Assumptions!$B$13/Assumptions!$B$36 -> 59640000 | F22: =Assumptions!$B$13/Assumptions!$B$36 -> 59640000 | G22: =Assumptions!$B$13/Assumptions!$B$36 -> 59640000 | H22: =Assumptions!$B$13/Assumptions!$B$36 -> 59640000 | I22: =Assumptions!$B$13/Assumptions!$B$36 -> 59640000 | J22: =Assumptions!$B$13/Assumptions!$B$36 -> 59640000 | K22: =Assumptions!$B$13/Assumptions!$B$36 -> 59640000 | ... AB22: =Assumptions!$B$13/Assumptions!$B$36 -> 59640000
A23: EBIT (EUR) | C23: 0 | D23: =D21-D22 -> 1.1788599e+08 | E23: =E21-E22 -> 1.1664739e+08 | F23: =F21-F22 -> 1.1538401e+08 | G23: =G21-G22 -> 1.1409536e+08 | H23: =H21-H22 -> 1.1278094e+08 | I23: =I21-I22 -> 1.1144023e+08 | J23: =J21-J22 -> 1.1007271e+08 | K23: =K21-K22 -> 1.0867784e+08 | ... AB23: =AB21-AB22 -> -60438295
A24: Tax (EUR) | C24: 0 | D24: =-MAX(0,D23*Assumptions!$B$32) -> -30414586 | E24: =-MAX(0,E23*Assumptions!$B$32) -> -30095026 | F24: =-MAX(0,F23*Assumptions!$B$32) -> -29769074 | G24: =-MAX(0,G23*Assumptions!$B$32) -> -29436603 | H24: =-MAX(0,H23*Assumptions!$B$32) -> -29097483 | I24: =-MAX(0,I23*Assumptions!$B$32) -> -28751580 | J24: =-MAX(0,J23*Assumptions!$B$32) -> -28398759 | K24: =-MAX(0,K23*Assumptions!$B$32) -> -28038882 | ... AB24: =-MAX(0,AB23*Assumptions!$B$32) -> 0
A25: CASH FLOW
A26: CAPEX (EUR) | C26: =-Assumptions!$B$13 -> -1491000000 | D26: 0 | E26: 0 | F26: 0 | G26: 0 | H26: 0 | I26: 0 | J26: 0 | K26: 0 | L26: 0 | M26: 0 | N26: 0 | O26: 0 | P26: 0 | Q26: 0 | R26: 0 | S26: 0 | T26: 0 | U26: 0 | V26: 0 | W26: 0 | X26: 0 | Y26: 0 | Z26: 0 | AA26: 0 | AB26: 0
A27: Decommissioning (EUR) | C27: 0 | D27: 0 | E27: 0 | F27: 0 | G27: 0 | H27: 0 | I27: 0 | J27: 0 | K27: 0 | L27: 0 | M27: 0 | N27: 0 | O27: 0 | P27: 0 | Q27: 0 | R27: 0 | S27: 0 | T27: 0 | U27: 0 | V27: 0 | W27: 0 | X27: 0 | Y27: 0 | Z27: 0 | AA27: 0 | AB27: =-Assumptions!$B$16 -> -42000000
A28: Free cash flow (EUR) | C28: =C26+C27 -> -1491000000 | D28: =D21+D24+D26+D27 -> 1.4711141e+08 | E28: =E21+E24+E26+E27 -> 1.4619236e+08 | F28: =F21+F24+F26+F27 -> 1.4525493e+08 | G28: =G21+G24+G26+G27 -> 1.4429876e+08 | H28: =H21+H24+H26+H27 -> 1.4332346e+08 | I28: =I21+I24+I26+I27 -> 1.4232865e+08 | J28: =J21+J24+J26+J27 -> 1.4131395e+08 | K28: =K21+K24+K26+K27 -> 1.4027895e+08 | ... AB28: =AB21+AB24+AB26+AB27 -> -42798295
A29: Discount factor | C29: 1 | D29: =1/(1+Assumptions!$B$33)^D5 -> 0.95878656 | E29: =1/(1+Assumptions!$B$33)^E5 -> 0.91927167 | F29: =1/(1+Assumptions!$B$33)^F5 -> 0.88138532 | G29: =1/(1+Assumptions!$B$33)^G5 -> 0.8450604 | H29: =1/(1+Assumptions!$B$33)^H5 -> 0.81023255 | I29: =1/(1+Assumptions!$B$33)^I5 -> 0.77684008 | J29: =1/(1+Assumptions!$B$33)^J5 -> 0.74482383 | K29: =1/(1+Assumptions!$B$33)^K5 -> 0.71412708 | ... AB29: =1/(1+Assumptions!$B$33)^AB5 -> 0.34917926
A30: Discounted cash flow (EUR) | C30: =C28*C29 -> -1491000000 | D30: =D28*D29 -> 1.4104844e+08 | E30: =E28*E29 -> 1.343905e+08 | F30: =F28*F29 -> 1.2802557e+08 | G30: =G28*G29 -> 1.2194117e+08 | H30: =H28*H29 -> 1.1612533e+08 | I30: =I28*I29 -> 1.105666e+08 | J30: =J28*J29 -> 1.05254e+08 | ... AB30: =AB28*AB29 -> -14944277
A31: Cumulative discounted (EUR) | C31: =C30 -> -1491000000 | D31: =C31+D30 -> -1.3499516e+09 | E31: =D31+E30 -> -1.2155611e+09 | F31: =E31+F30 -> -1.0875355e+09 | G31: =F31+G30 -> -9.6559433e+08 | H31: =G31+H30 -> -8.49469e+08 | I31: =H31+I30 -> -7.389024e+08 | J31: =I31+J30 -> -6.336484e+08 | K31: =J31+K30 -> -5.334714e+08 | ... AB31: =AA31+AB30 -> 63457758
A32: Discounted production (MWh) | C32: 0 | D32: =D10*D29 -> 3158012.8 | E32: =E10*E29 -> 3027860.2 | F32: =F10*F29 -> 2903071.7 | G32: =G10*G29 -> 2783426.1 | H32: =H10*H29 -> 2668711.6 | I32: =I10*I29 -> 2558724.8 | J32: =J10*J29 -> 2453270.9 | K32: =K10*K29 -> 2352163.2 | ... AB32: =AB10*AB29 -> 1150112.7
A35: OUTPUTS
A36: NPV (EUR) | B36: =SUM(C30:AB30) -> 63457758
A37: NPV (EUR m) | B37: =B36/1000000 -> 63.457758
A38: IRR | B38: =IRR(C28:AB28) -> 0.049112779
A39: Payback (disc. years) | B39: =COUNTIF(C31:AB31,"<0") -> 15
A40: LCOE (EUR/MWh) | B40: =(-SUM(C26:AB26)-SUM(C27:AB27)+SUMPRODUCT(C19:AB19,C29:AB29))/SUM(C32:AB32) -> 53.817553

Sheet Ex-Post
A1: Model Ex-Post (actual prices)
A4: Calendar year | C4: =Assumptions!$B$35-1 -> 2020 | D4: =Assumptions!$B$35+0 -> 2021 | E4: =Assumptions!$B$35+1 -> 2022 | F4: =Assumptions!$B$35+2 -> 2023 | G4: =Assumptions!$B$35+3 -> 2024 | H4: =Assumptions!$B$35+4 -> 2025 | I4: =Assumptions!$B$35+5 -> 2026 | J4: =Assumptions!$B$35+6 -> 2027 | K4: =Assumptions!$B$35+7 -> 2028 | L4: =Assumptions!$B$35+8 -> 2029 | M4: =Assumptions!$B$35+9 -> 2030 | N4: =Assumptions!$B$35+10 -> 2031 | O4: =Assumptions!$B$35+11 -> 2032 | P4: =Assumptions!$B$35+12 -> 2033 | Q4: =Assumptions!$B$35+13 -> 2034 | R4: =Assumptions!$B$35+14 -> 2035 | S4: =Assumptions!$B$35+15 -> 2036 | T4: =Assumptions!$B$35+16 -> 2037 | U4: =Assumptions!$B$35+17 -> 2038 | V4: =Assumptions!$B$35+18 -> 2039 | W4: =Assumptions!$B$35+19 -> 2040 | X4: =Assumptions!$B$35+20 -> 2041 | Y4: =Assumptions!$B$35+21 -> 2042 | Z4: =Assumptions!$B$35+22 -> 2043 | AA4: =Assumptions!$B$35+23 -> 2044 | AB4: =Assumptions!$B$35+24 -> 2045
A5: Operational year | C5: 0 | D5: 1 | E5: 2 | F5: 3 | G5: 4 | H5: 5 | I5: 6 | J5: 7 | K5: 8 | L5: 9 | M5: 10 | N5: 11 | O5: 12 | P5: 13 | Q5: 14 | R5: 15 | S5: 16 | T5: 17 | U5: 18 | V5: 19 | W5: 20 | X5: 21 | Y5: 22 | Z5: 23 | AA5: 24 | AB5: 25
A6: Subsidy active (1/0) | C6: 0 | D6: =IF(D5<=Assumptions!$B$24,1,0) -> 1 | E6: =IF(E5<=Assumptions!$B$24,1,0) -> 1 | F6: =IF(F5<=Assumptions!$B$24,1,0) -> 1 | G6: =IF(G5<=Assumptions!$B$24,1,0) -> 1 | H6: =IF(H5<=Assumptions!$B$24,1,0) -> 1 | I6: =IF(I5<=Assumptions!$B$24,1,0) -> 1 | J6: =IF(J5<=Assumptions!$B$24,1,0) -> 1 | K6: =IF(K5<=Assumptions!$B$24,1,0) -> 1 | ... AB6: =IF(AB5<=Assumptions!$B$24,1,0) -> 0
A8: PRODUCTION
A9: Degradation factor | C9: 0 | D9: =(1-Assumptions!$B$10)^(D5-1) -> 1 | E9: =(1-Assumptions!$B$10)^(E5-1) -> 1 | F9: =(1-Assumptions!$B$10)^(F5-1) -> 1 | G9: =(1-Assumptions!$B$10)^(G5-1) -> 1 | H9: =(1-Assumptions!$B$10)^(H5-1) -> 1 | I9: =(1-Assumptions!$B$10)^(I5-1) -> 1 | J9: =(1-Assumptions!$B$10)^(J5-1) -> 1 | K9: =(1-Assumptions!$B$10)^(K5-1) -> 1 | ... AB9: =(1-Assumptions!$B$10)^(AB5-1) -> 1
A10: Net production (MWh) | C10: 0 | D10: =Assumptions!$B$9*D9 -> 3293760 | E10: =Assumptions!$B$9*E9 -> 3293760 | F10: =Assumptions!$B$9*F9 -> 3293760 | G10: =Assumptions!$B$9*G9 -> 3293760 | H10: =Assumptions!$B$9*H9 -> 3293760 | I10: =Assumptions!$B$9*I9 -> 3293760 | J10: =Assumptions!$B$9*J9 -> 3293760 | K10: =Assumptions!$B$9*K9 -> 3293760 | ... AB10: =Assumptions!$B$9*AB9 -> 3293760
A11: REVENUE
A12: Market price (EUR/MWh) | C12: 0 | D12: =IFERROR(VLOOKUP(D4,'Price Data'!$E$5:$F$16,2,FALSE()),Assumptions!$B$26) -> 102.64833 | E12: =IFERROR(VLOOKUP(E4,'Price Data'!$E$5:$F$16,2,FALSE()),Assumptions!$B$26) -> 241.20417 | F12: =IFERROR(VLOOKUP(F4,'Price Data'!$E$5:$F$16,2,FALSE()),Assumptions!$B$26) -> 96.134167 | G12: =IFERROR(VLOOKUP(G4,'Price Data'!$E$5:$F$16,2,FALSE()),Assumptions!$B$26) -> 77.239167 | H12: =IFERROR(VLOOKUP(H4,'Price Data'!$E$5:$F$16,2,FALSE()),Assumptions!$B$26) -> 87.55 | I12: =IFERROR(VLOOKUP(I4,'Price Data'!$E$5:$F$16,2,FALSE()),Assumptions!$B$26) -> 96.497143 | J12: =IFERROR(VLOOKUP(J4,'Price Data'!$E$5:$F$16,2,FALSE()),Assumptions!$B$26) -> 80 | K12: =IFERROR(VLOOKUP(K4,'Price Data'!$E$5:$F$16,2,FALSE()),Assumptions!$B$26) -> 80 | ... AB12: =IFERROR(VLOOKUP(AB4,'Price Data'!$E$5:$F$16,2,FALSE()),Assumptions!$B$26) -> 80
A13: Subsidy (EUR/MWh) | C13: 0 | D13: =IF(D6=1,MAX(0,Assumptions!$B$22-MAX(D12,Assumptions!$B$23)),0) -> 0 | E13: =IF(E6=1,MAX(0,Assumptions!$B$22-MAX(E12,Assumptions!$B$23)),0) -> 0 | F13: =IF(F6=1,MAX(0,Assumptions!$B$22-MAX(F12,Assumptions!$B$23)),0) -> 0 | G13: =IF(G6=1,MAX(0,Assumptions!$B$22-MAX(G12,Assumptions!$B$23)),0) -> 0 | H13: =IF(H6=1,MAX(0,Assumptions!$B$22-MAX(H12,Assumptions!$B$23)),0) -> 0 | I13: =IF(I6=1,MAX(0,Assumptions!$B$22-MAX(I12,Assumptions!$B$23)),0) -> 0 | J13: =IF(J6=1,MAX(0,Assumptions!$B$22-MAX(J12,Assumptions!$B$23)),0) -> 0 | K13: =IF(K6=1,MAX(0,Assumptions!$B$22-MAX(K12,Assumptions!$B$23)),0) -> 0 | ... AB13: =IF(AB6=1,MAX(0,Assumptions!$B$22-MAX(AB12,Assumptions!$B$23)),0) -> 0
A14: Total price (EUR/MWh) | C14: 0 | D14: =D12+D13 -> 102.64833 | E14: =E12+E13 -> 241.20417 | F14: =F12+F13 -> 96.134167 | G14: =G12+G13 -> 77.239167 | H14: =H12+H13 -> 87.55 | I14: =I12+I13 -> 96.497143 | J14: =J12+J13 -> 80 | K14: =K12+K13 -> 80 | ... AB14: =AB12+AB13 -> 80
A15: Total revenue (EUR) | C15: 0 | D15: =D10*D14 -> 3.3809897e+08 | E15: =E10*E14 -> 794468636 | F15: =F10*F14 -> 3.1664287e+08 | G15: =G10*G14 -> 2.5440728e+08 | H15: =H10*H14 -> 288368688 | I15: =I10*I14 -> 3.1783843e+08 | J15: =J10*J14 -> 263500800 | K15: =K10*K14 -> 263500800 | ... AB15: =AB10*AB14 -> 263500800
A16: COSTS
A17: OPEX variable (EUR) | C17: 0 | D17: =Assumptions!$B$18*(1+Assumptions!$B$20)^(D5-1)*D10 -> 31587158 | E17: =Assumptions!$B$18*(1+Assumptions!$B$20)^(E5-1)*E10 -> 32218902 | F17: =Assumptions!$B$18*(1+Assumptions!$B$20)^(F5-1)*F10 -> 32863280 | G17: =Assumptions!$B$18*(1+Assumptions!$B$20)^(G5-1)*G10 -> 33520545 | H17: =Assumptions!$B$18*(1+Assumptions!$B$20)^(H5-1)*H10 -> 34190956 | I17: =Assumptions!$B$18*(1+Assumptions!$B$20)^(I5-1)*I10 -> 34874775 | J17: =Assumptions!$B$18*(1+Assumptions!$B$20)^(J5-1)*J10 -> 35572271 | K17: =Assumptions!$B$18*(1+Assumptions!$B$20)^(K5-1)*K10 -> 36283716 | ... AB17: =Assumptions!$B$18*(1+Assumptions!$B$20)^(AB5-1)*AB10 -> 50805962
A18: OPEX fixed (EUR) | C18: 0 | D18: =Assumptions!$B$19*(1+Assumptions!$B$20)^(D5-1)*Assumptions!$B$6 -> 30343200 | E18: =Assumptions!$B$19*(1+Assumptions!$B$20)^(E5-1)*Assumptions!$B$6 -> 30950064 | F18: =Assumptions!$B$19*(1+Assumptions!$B$20)^(F5-1)*Assumptions!$B$6 -> 31569065 | G18: =Assumptions!$B$19*(1+Assumptions!$B$20)^(G5-1)*Assumptions!$B$6 -> 32200447 | H18: =Assumptions!$B$19*(1+Assumptions!$B$20)^(H5-1)*Assumptions!$B$6 -> 32844456 | I18: =Assumptions!$B$19*(1+Assumptions!$B$20)^(I5-1)*Assumptions!$B$6 -> 33501345 | J18: =Assumptions!$B$19*(1+Assumptions!$B$20)^(J5-1)*Assumptions!$B$6 -> 34171372 | K18: =Assumptions!$B$19*(1+Assumptions!$B$20)^(K5-1)*Assumptions!$B$6 -> 34854799 | ... AB18: =Assumptions!$B$19*(1+Assumptions!$B$20)^(AB5-1)*Assumptions!$B$6 -> 48805133
A19: Total OPEX (EUR) | C19: 0 | D19: =D17+D18 -> 61930358 | E19: =E17+E18 -> 63168966 | F19: =F17+F18 -> 64432345 | G19: =G17+G18 -> 65720992 | H19: =H17+H18 -> 67035412 | I19: =I17+I18 -> 68376120 | J19: =J17+J18 -> 69743642 | K19: =K17+K18 -> 71138515 | ... AB19: =AB17+AB18 -> 99611095
A20: RESULT
A21: EBITDA (EUR) | C21: 0 | D21: =D15-D19 -> 276168616 | E21: =E15-E19 -> 7.3129967e+08 | F21: =F15-F19 -> 2.5221053e+08 | G21: =G15-G19 -> 1.8868629e+08 | H21: =H15-H19 -> 2.2133328e+08 | I21: =I15-I19 -> 2.4946231e+08 | J21: =J15-J19 -> 1.9375716e+08 | K21: =K15-K19 -> 1.9236228e+08 | ... AB21: =AB15-AB19 -> 1.638897e+08
A22: Depreciation (EUR) | C22: 0 | D22: =Assumptions!$B$13/Assumptions!$B$36 -> 59640000 | E22: =Assumptions!$B$13/Assumptions!$B$36 -> 59640000 | F22: =Assumptions!$B$13/Assumptions!$B$36 -> 59640000 | G22: =Assumptions!$B$13/Assumptions!$B$36 -> 59640000 | H22: =Assumptions!$B$13/Assumptions!$B$36 -> 59640000 | I22: =Assumptions!$B$13/Assumptions!$B$36 -> 59640000 | J22: =Assumptions!$B$13/Assumptions!$B$36 -> 59640000 | K22: =Assumptions!$B$13/Assumptions!$B$36 -> 59640000 | ... AB22: =Assumptions!$B$13/Assumptions!$B$36 -> 59640000
A23: EBIT (EUR) | C23: 0 | D23: =D21-D22 -> 216528616 | E23: =E21-E22 -> 6.7165967e+08 | F23: =F21-F22 -> 1.9257053e+08 | G23: =G21-G22 -> 1.2904629e+08 | H23: =H21-H22 -> 1.6169328e+08 | I23: =I21-I22 -> 1.8982231e+08 | J23: =J21-J22 -> 1.3411716e+08 | K23: =K21-K22 -> 1.3272228e+08 | ... AB23: =AB21-AB22 -> 1.042497e+08
A24: Tax (EUR) | C24: 0 | D24: =-MAX(0,D23*Assumptions!$B$32) -> -55864383 | E24: =-MAX(0,E23*Assumptions!$B$32) -> -1.7328819e+08 | F24: =-MAX(0,F23*Assumptions!$B$32) -> -49683196 | G24: =-MAX(0,G23*Assumptions!$B$32) -> -33293942 | H24: =-MAX(0,H23*Assumptions!$B$32) -> -41716865 | I24: =-MAX(0,I23*Assumptions!$B$32) -> -48974156 | J24: =-MAX(0,J23*Assumptions!$B$32) -> -34602227 | K24: =-MAX(0,K23*Assumptions!$B$32) -> -34242350 | ... AB24: =-MAX(0,AB23*Assumptions!$B$32) -> -26896424
A25: CASH FLOW
A26: CAPEX (EUR) | C26: =-Assumptions!$B$13 -> -1491000000 | D26: 0 | E26: 0 | F26: 0 | G26: 0 | H26: 0 | I26: 0 | J26: 0 | K26: 0 | L26: 0 | M26: 0 | N26: 0 | O26: 0 | P26: 0 | Q26: 0 | R26: 0 | S26: 0 | T26: 0 | U26: 0 | V26: 0 | W26: 0 | X26: 0 | Y26: 0 | Z26: 0 | AA26: 0 | AB26: 0
A27: Decommissioning (EUR) | C27: 0 | D27: 0 | E27: 0 | F27: 0 | G27: 0 | H27: 0 | I27: 0 | J27: 0 | K27: 0 | L27: 0 | M27: 0 | N27: 0 | O27: 0 | P27: 0 | Q27: 0 | R27: 0 | S27: 0 | T27: 0 | U27: 0 | V27: 0 | W27: 0 | X27: 0 | Y27: 0 | Z27: 0 | AA27: 0 | AB27: =-Assumptions!$B$16 -> -42000000
A28: Free cash flow (EUR) | C28: =C26+C27 -> -1491000000 | D28: =D21+D24+D26+D27 -> 2.2030423e+08 | E28: =E21+E24+E26+E27 -> 5.5801148e+08 | F28: =F21+F24+F26+F27 -> 2.0252733e+08 | G28: =G21+G24+G26+G27 -> 1.5539234e+08 | H28: =H21+H24+H26+H27 -> 1.7961641e+08 | I28: =I21+I24+I26+I27 -> 2.0048815e+08 | J28: =J21+J24+J26+J27 -> 1.5915493e+08 | K28: =K21+K24+K26+K27 -> 1.5811994e+08 | ... AB28: =AB21+AB24+AB26+AB27 -> 94993281
A29: Discount factor | C29: 1 | D29: =1/(1+Assumptions!$B$33)^D5 -> 0.95878656 | E29: =1/(1+Assumptions!$B$33)^E5 -> 0.91927167 | F29: =1/(1+Assumptions!$B$33)^F5 -> 0.88138532 | G29: =1/(1+Assumptions!$B$33)^G5 -> 0.8450604 | H29: =1/(1+Assumptions!$B$33)^H5 -> 0.81023255 | I29: =1/(1+Assumptions!$B$33)^I5 -> 0.77684008 | J29: =1/(1+Assumptions!$B$33)^J5 -> 0.74482383 | K29: =1/(1+Assumptions!$B$33)^K5 -> 0.71412708 | ... AB29: =1/(1+Assumptions!$B$33)^AB5 -> 0.34917926
A30: Discounted cash flow (EUR) | C30: =C28*C29 -> -1491000000 | D30: =D28*D29 -> 2.1122474e+08 | E30: =E28*E29 -> 5.1296414e+08 | F30: =F28*F29 -> 1.7850462e+08 | G30: =G28*G29 -> 1.3131592e+08 | H30: =H28*H29 -> 1.4553106e+08 | I30: =I28*I29 -> 1.5574723e+08 | J30: =J28*J29 -> 1.1854239e+08 | ... AB30: =AB28*AB29 -> 33169683
A31: Cumulative discounted (EUR) | C31: =C30 -> -1491000000 | D31: =C31+D30 -> -1.2797753e+09 | E31: =D31+E30 -> -7.6681112e+08 | F31: =E31+F30 -> -5.8830651e+08 | G31: =F31+G30 -> -4.5699059e+08 | H31: =G31+H30 -> -3.1145953e+08 | I31: =H31+I30 -> -1.5571229e+08 | J31: =I31+J30 -> -37169908 | K31: =J31+K30 -> 75747819 | ... AB31: =AA31+AB30 -> 1.3241953e+09
A32: Discounted production (MWh) | C32: 0 | D32: =D10*D29 -> 3158012.8 | E32: =E10*E29 -> 3027860.2 | F32: =F10*F29 -> 2903071.7 | G32: =G10*G29 -> 2783426.1 | H32: =H10*H29 -> 2668711.6 | I32: =I10*I29 -> 2558724.8 | J32: =J10*J29 -> 2453270.9 | K32: =K10*K29 -> 2352163.2 | ... AB32: =AB10*AB29 -> 1150112.7
A35: OUTPUTS
A36: NPV (EUR) | B36: =SUM(C30:AB30) -> 1.3241953e+09
A37: NPV (EUR m) | B37: =B36/1000000 -> 1324.1953
A38: IRR | B38: =IRR(C28:AB28) -> 0.14000418
A39: Payback (disc. years) | B39: =COUNTIF(C31:AB31,"<0") -> 8
A40: LCOE (EUR/MWh) | B40: =(-SUM(C26:AB26)-SUM(C27:AB27)+SUMPRODUCT(C19:AB19,C29:AB29))/SUM(C32:AB32) -> 53.817553

Sheet Dashboard
A1: Key outputs
A4: Metric | B4: Ex-ante | C4: Ex-Post | D4: Note
A5: NPV (EUR m) | B5: ='Model (ex-ante)'!$B$37 -> 63.457758 | C5: ='Ex-Post'!$B$37 -> 1324.1953 | D5: Net present value
A6: IRR | B6: ='Model (ex-ante)'!$B$38 -> 0.049112779 | C6: ='Ex-Post'!$B$38 -> 0.14000418 | D6: Internal rate of return (unlevered)
A7: Payback (disc. years) | B7: ='Model (ex-ante)'!$B$39 -> 15 | C7: ='Ex-Post'!$B$39 -> 8 | D7: Years until cumulative PV turns positive
A8: LCOE (EUR/MWh) | B8: ='Model (ex-ante)'!$B$40 -> 53.817553 | C8: ='Ex-Post'!$B$40 -> 53.817553 | D8: Levelized cost of energy
A10: CREG CAPEX check (ex-ante)
A11: Metric | B11: Value
A12: Extra CAPEX vs EIB (EUR m) | B12: =((Assumptions!$B$14-Assumptions!$B$12)*1000000)/1000000 -> 400
A13: PV extra depreciation tax shield (EUR m) | B13: =((Assumptions!$B$14-Assumptions!$B$12)*1000000)/Assumptions!$B$36*Assumptions!$B$32*((1-(1+Assumptions!$B$33)^-Assumptions!$B$36)/Assumptions!$B$33)/1000000 -> 62.500594
A14: Ex-ante NPV with CREG CAPEX (EUR m) | B14: ='Model (ex-ante)'!$B$37-B12+B13 -> -274.04165
A15: A negative NPV here shows the 2016 bid only worked with costs below the CREG estimate.
A17: Valuation benchmarks
A18: Source | B18: EUR m | C18: Type | D18: Use
A19: EIB total cost | B19: 1491 | C19: Construction cost | D19: CAPEX basis in the model
A20: CREG estimate | B20: 1891 | C20: Construction cost (2016) | D20: Comparison / bid check above
A21: Norges Bank implied equity | B21: 2750 | C21: Equity value 2021 | D21: Benchmark for the DCF equity value
